featurecraft/__init__.py
featurecraft/aggregations.py
featurecraft/cli.py
featurecraft/clustering.py
featurecraft/config.py
featurecraft/domain.py
featurecraft/drift.py
featurecraft/encoders.py
featurecraft/exceptions.py
featurecraft/explainability.py
featurecraft/imbalance.py
featurecraft/imputers.py
featurecraft/insights.py
featurecraft/interactions.py
featurecraft/interactive.py
featurecraft/io.py
featurecraft/logging.py
featurecraft/pipeline.py
featurecraft/plots.py
featurecraft/reducers.py
featurecraft/registry.py
featurecraft/report.py
featurecraft/scalers.py
featurecraft/selection.py
featurecraft/settings.py
featurecraft/shap_utils.py
featurecraft/statistical.py
featurecraft/text.py
featurecraft/time_series.py
featurecraft/transformers.py
featurecraft/types.py
featurecraft/validators.py
featurecraft/version.py
featurecraft/templates/report.html.j2
featurecraft/utils/__init__.py
featurecraft/utils/leakage.py
featurecraft/validation/__init__.py
featurecraft/validation/schema_validator.py
featurecraft-1.0.0.dist-info/METADATA
featurecraft-1.0.0.dist-info/WHEEL
featurecraft-1.0.0.dist-info/entry_points.txt
featurecraft-1.0.0.dist-info/licenses/LICENSE
featurecraft-1.0.0.dist-info/RECORD
