Metadata-Version: 2.4
Name: featurecraft
Version: 1.0.0
Summary: Automatic feature engineering, insights, and sklearn pipelines for tabular ML with optional time-series support.
Project-URL: Homepage, https://github.com/featurecraft/featurecraft
Project-URL: Repository, https://github.com/featurecraft/featurecraft
Project-URL: Issues, https://github.com/featurecraft/featurecraft/issues
Project-URL: Documentation, https://github.com/featurecraft/featurecraft/blob/main/docs/quickstart.md
Author-email: FeatureCraft Authors <maintainers@featurecraft.dev>
License-Expression: MIT
License-File: LICENSE
Keywords: auto,feature engineering,machine learning,sklearn,tabular,time series
Classifier: Development Status :: 3 - Alpha
Classifier: Intended Audience :: Developers
Classifier: Intended Audience :: Science/Research
Classifier: License :: OSI Approved :: MIT License
Classifier: Operating System :: OS Independent
Classifier: Programming Language :: Python :: 3
Classifier: Topic :: Scientific/Engineering :: Artificial Intelligence
Requires-Python: >=3.9
Requires-Dist: anthropic>=0.18
Requires-Dist: category-encoders>=2.6
Requires-Dist: imbalanced-learn>=0.10
Requires-Dist: jinja2>=3.1
Requires-Dist: joblib>=1.3
Requires-Dist: matplotlib>=3.9.0
Requires-Dist: numpy>=1.23
Requires-Dist: openai>=1.0
Requires-Dist: pandas>=1.5
Requires-Dist: pandera>=0.17
Requires-Dist: pillow>=10.0.0
Requires-Dist: pydantic>=2.5
Requires-Dist: rich>=13.3
Requires-Dist: scikit-learn>=1.3
Requires-Dist: scipy>=1.10
Requires-Dist: shap>=0.44
Requires-Dist: tiktoken>=0.5
Requires-Dist: typer>=0.9
Provides-Extra: dev
Requires-Dist: bandit>=1.7; extra == 'dev'
Requires-Dist: black>=23.0; extra == 'dev'
Requires-Dist: build>=1.0; extra == 'dev'
Requires-Dist: hypothesis>=6.82; extra == 'dev'
Requires-Dist: mypy>=1.5; extra == 'dev'
Requires-Dist: pip-audit>=2.6; extra == 'dev'
Requires-Dist: pre-commit>=3.5; extra == 'dev'
Requires-Dist: pytest-cov>=4.1; extra == 'dev'
Requires-Dist: pytest-xdist>=3.3; extra == 'dev'
Requires-Dist: pytest>=7.4; extra == 'dev'
Requires-Dist: ruff>=0.1.0; extra == 'dev'
Requires-Dist: twine>=4.0; extra == 'dev'
